{
   "accentFromPage": false,
   "accentOnWindow": true,
   "accentSaturationLimit": 1,
   "alpha": 1,
   "backgroundImage": "",
   "backgroundPosition": "stretch",
   "blur": 0,
   "colorAccentBg": "#292e42",
   "colorBg": "#1a1b26",
   "colorFg": "#c0caf5",
   "colorHighlightBg": "#9ece6a",
   "colorWindowBg": "#15161e",
   "contrast": 0,
   "dimBlurred": false,
   "engineVersion": 1,
   "id": "2699b36b-bc7e-44b3-95f4-26c91f810016",
   "name": "Tokyo Night (Green)",
   "preferSystemAccent": false,
   "radius": 14,
   "simpleScrollbar": true,
   "transparencyTabBar": false,
   "transparencyTabs": false,
   "url": "https://github.com/folke/tokyonight.nvim",
   "version": 1
}